import_embargo/__init__.py
import_embargo/__main__.py
import_embargo/core.py
import_embargo-0.0.1.dist-info/LICENSE
import_embargo-0.0.1.dist-info/METADATA
import_embargo-0.0.1.dist-info/WHEEL
import_embargo-0.0.1.dist-info/entry_points.txt
import_embargo-0.0.1.dist-info/RECORD
