Metadata-Version: 2.1
Name: import-embargo
Version: 0.0.1
Summary: Tool for limiting python imports to different packages and reporting violations.
Home-page: https://github.com/KlemenS189/import-embargo
License: MIT
Keywords: automation,lint,imports,ast
Author: Klemen Štrajhar
Author-email: klemen.strajhar@gmail.com
Requires-Python: >=3.10
Classifier: License :: OSI Approved :: MIT License
Classifier: Operating System :: OS Independent
Classifier: Programming Language :: Python :: 3
Classifier: Programming Language :: Python :: 3.10
Classifier: Programming Language :: Python :: 3.11
Classifier: Programming Language :: Python :: 3.12
Classifier: Topic :: Software Development :: Libraries
Classifier: Topic :: Utilities
Project-URL: Repository, https://github.com/KlemenS189/import-embargo
